duo_universal_auth/__init__.py
duo_universal_auth/apps.py
duo_universal_auth/middleware.py
duo_universal_auth/urls.py
duo_universal_auth/views.py
django_duo_universal_auth-0.2.0.dist-info/LICENSE
django_duo_universal_auth-0.2.0.dist-info/METADATA
django_duo_universal_auth-0.2.0.dist-info/WHEEL
django_duo_universal_auth-0.2.0.dist-info/top_level.txt
django_duo_universal_auth-0.2.0.dist-info/RECORD
