Metadata-Version: 2.1
Name: django-duo-universal-auth
Version: 0.2.0
Summary: A simple Django middleware for Duo Universal 2-factor authentication.
Home-page: https://github.com/AdamAngle/django-duo-universal-auth
Author: Adam Angle
Author-email: contact@adamangle.com
License: BSD 3-clause
Platform: UNKNOWN
Classifier: Environment :: Web Environment
Classifier: Framework :: Django
Classifier: Intended Audience :: Developers
Classifier: License :: OSI Approved :: BSD License
Classifier: Operating System :: OS Independent
Classifier: Programming Language :: Python
Classifier: Programming Language :: Python :: 3
Classifier: Topic :: Internet :: WWW/HTTP
Classifier: Topic :: Internet :: WWW/HTTP :: Dynamic Content
Requires-Dist: duo-universal
